baml_cc-0.209.0.10.dist-info/METADATA
baml_cc-0.209.0.10.dist-info/WHEEL
baml_cc-0.209.0.10.dist-info/licenses/LICENSE
baml_claude_code/client.py
baml_claude_code/__init__.py
baml_claude_code/ffi.py
baml_claude_code/error.py
baml_claude_code/provider.py
baml_claude_code/cli.py
baml_claude_code/baml_claude_code/__init__.py
baml_claude_code/baml_claude_code/ffi.py
baml_claude_code/baml_claude_code/baml_claude_code.so
baml_cc-0.209.0.10.dist-info/RECORD
