Metadata-Version: 2.3
Name: baml-cc
Version: 0.209.0.10
Classifier: Development Status :: 5 - Production/Stable
Classifier: Intended Audience :: Developers
Classifier: License :: OSI Approved :: Apache Software License
Classifier: Programming Language :: Python :: 3
Classifier: Programming Language :: Python :: 3.8
Classifier: Programming Language :: Python :: 3.9
Classifier: Programming Language :: Python :: 3.10
Classifier: Programming Language :: Python :: 3.11
Classifier: Programming Language :: Python :: 3.12
Classifier: Programming Language :: Rust
Classifier: Topic :: Software Development :: Libraries :: Python Modules
Classifier: Topic :: Scientific/Engineering :: Artificial Intelligence
Requires-Dist: baml-cc-py >=0.208.5.4
Requires-Dist: anthropic >=0.7.0
Requires-Dist: pydantic >=2.0.0
Requires-Dist: cffi >=1.15.0
Requires-Dist: pytest >=7.0.0 ; extra == 'dev'
Requires-Dist: pytest-asyncio >=0.21.0 ; extra == 'dev'
Requires-Dist: black >=23.0.0 ; extra == 'dev'
Requires-Dist: ruff >=0.1.0 ; extra == 'dev'
Requires-Dist: mypy >=1.0.0 ; extra == 'dev'
Provides-Extra: dev
License-File: LICENSE
Summary: BAML Claude Code Provider - Advanced Claude Code integration for BAML
Keywords: baml,claude,ai,llm,anthropic
Home-Page: https://github.com/ViperJuice/baml-cc
Author: ViperJuice <your-email@example.com>
Author-email: ViperJuice <your-email@example.com>
License: Apache-2.0
Requires-Python: >=3.9
Project-URL: Homepage, https://github.com/ViperJuice/baml-cc
Project-URL: Repository, https://github.com/ViperJuice/baml-cc
Project-URL: Documentation, https://github.com/ViperJuice/baml-cc#readme
Project-URL: Bug Tracker, https://github.com/ViperJuice/baml-cc/issues
